document_clustering/clustering.py
document_clustering/qkld_sim.cpython-310-x86_64-linux-gnu.so
document_clustering/qkld_sim.pyi
document_clustering/qkld_sim.pyx
document_clustering-0.1.1.dist-info/METADATA
document_clustering-0.1.1.dist-info/WHEEL
document_clustering-0.1.1.dist-info/RECORD
