Metadata-Version: 2.1
Name: document-clustering
Version: 0.1.1
Summary: Clustering algorithms for text collections
Author: Gijs Hendriksen
Author-email: info@gijshendriksen.nl
Requires-Python: >=3.10,<4.0
Classifier: Programming Language :: Python :: 3
Classifier: Programming Language :: Python :: 3.10
Classifier: Programming Language :: Python :: 3.11
Requires-Dist: ir-datasets (>=0.5.6,<0.6.0)
Requires-Dist: scikit-learn (>=1.4.2,<2.0.0)
